LICENSE
README.md
botsislabutils/__init__.py
botsislabutils/authentication_manager.py
botsislabutils/authorization_manager.py
botsislabutils/config_manager.py
botsislabutils/logger.py
botsislabutils/mysql_interface.py
botsislabutils/service_utility.py
botsislabutils-1.0.2.dist-info/METADATA
botsislabutils-1.0.2.dist-info/WHEEL
botsislabutils-1.0.2.dist-info/licenses/LICENSE
botsislabutils-1.0.2.dist-info/RECORD
