Metadata-Version: 2.4
Name: botsislabutils
Version: 1.0.2
Summary: Commonly used utilities for Botsis Lab
Project-URL: Homepage, https://gitlab.com/botsis-lab/botsis-lab-utilities
Project-URL: Bug Tracker, https://gitlab.com/botsis-lab/botsis-lab-utilities/-/issues
Author-email: Jonathan Spiker <jspiker3@jhmi.edu>, Kory Kreimeyer <kkreime1@jhu.edu>, Taxiarchis Botsis <tbotsis1@jhmi.edu>
License-Expression: MIT
License-File: LICENSE
Classifier: License :: OSI Approved :: MIT License
Classifier: Operating System :: OS Independent
Classifier: Programming Language :: Python :: 3
Requires-Python: >=3.6
Requires-Dist: flask>=2.0
Requires-Dist: mysql-connector-python>=8.0
